django_polars_tools/__init__.py
django_polars_tools/main.py
django_polars_tools/py.typed
django_polars_tools-0.1.2.dist-info/licenses/LICENSE
django_polars_tools-0.1.2.dist-info/WHEEL
django_polars_tools-0.1.2.dist-info/METADATA
django_polars_tools-0.1.2.dist-info/RECORD
