Metadata-Version: 2.4
Name: django-polars-tools
Version: 0.1.2
Summary: Tools for converting Django QuerySets to Polars DataFrames with correct schema handling, nullable field support, and high-performance data extraction.
Keywords: django,polars,dataframe,queryset,orm,data-analysis
Author: Marc
Author-email: Marc <codebymarc@pm.me>
License-Expression: MIT
License-File: LICENSE
Classifier: Development Status :: 3 - Alpha
Classifier: Intended Audience :: Developers
Classifier: License :: OSI Approved :: MIT License
Classifier: Programming Language :: Python :: 3
Classifier: Programming Language :: Python :: 3 :: Only
Classifier: Programming Language :: Python :: 3.10
Classifier: Programming Language :: Python :: 3.11
Classifier: Programming Language :: Python :: 3.12
Classifier: Programming Language :: Python :: 3.13
Classifier: Programming Language :: Python :: 3.14
Classifier: Framework :: Django
Classifier: Framework :: Django :: 4.2
Classifier: Framework :: Django :: 5.1
Classifier: Framework :: Django :: 5.2
Classifier: Topic :: Software Development :: Libraries :: Python Modules
Classifier: Topic :: Database
Requires-Dist: django>=4.2
Requires-Dist: polars>=0.20.0
Requires-Dist: pytest>=7.0 ; extra == 'dev'
Requires-Dist: pytest-cov>=4.0 ; extra == 'dev'
Requires-Dist: ruff>=0.8.0 ; extra == 'dev'
Requires-Dist: tox>=4.0 ; extra == 'dev'
Requires-Dist: mypy>=1.0 ; extra == 'dev'
Requires-Dist: django-stubs>=4.2 ; extra == 'dev'
Requires-Python: >=3.10
Project-URL: Repository, https://github.com/code-by-marc/django-polars-tools
Project-URL: Issues, https://github.com/code-by-marc/django-polars-tools/issues
Provides-Extra: dev
